setup.cfg
setup.py
healthcheck/__init__.py
healthcheck.egg-info/PKG-INFO
healthcheck.egg-info/SOURCES.txt
healthcheck.egg-info/dependency_links.txt
healthcheck.egg-info/not-zip-safe
healthcheck.egg-info/top_level.txt
tests/__init__.py
tests/test_unit/__init__.py
tests/test_unit/test_healthcheck.py