Metadata-Version: 1.1
Name: healthcheck
Version: 1.3.1
Summary: Adds healthcheck endpoints to Flask apps
Home-page: https://github.com/Runscope/healthcheck
Author: Frank Stratton
Author-email: frank@runscope.com
License: MIT
Download-URL: https://github.com/Runscope/healthcheck/tarball/1.3.1
Platform: any
Classifier: Development Status :: 5 - Production/Stable
Classifier: Environment :: Web Environment
Classifier: Framework :: Flask
Classifier: Programming Language :: Python
